electricitycostcalculator_gabetest/__init__.py
electricitycostcalculator_gabetest/__init__.py.bak
electricitycostcalculator_gabetest/cost_calculator/.gitignore
electricitycostcalculator_gabetest/cost_calculator/__init__.py
electricitycostcalculator_gabetest/cost_calculator/__init__.py.bak
electricitycostcalculator_gabetest/cost_calculator/cost_calculator.py
electricitycostcalculator_gabetest/cost_calculator/cost_calculator.py.bak
electricitycostcalculator_gabetest/cost_calculator/rate_structure.py
electricitycostcalculator_gabetest/cost_calculator/rate_structure.py.bak
electricitycostcalculator_gabetest/cost_calculator/tariff_structure.py
electricitycostcalculator_gabetest/cost_calculator/tariff_structure.py.bak
electricitycostcalculator_gabetest/oadr_signal/.gitignore
electricitycostcalculator_gabetest/oadr_signal/DR_template.py
electricitycostcalculator_gabetest/oadr_signal/DR_template.py.bak
electricitycostcalculator_gabetest/oadr_signal/__init__.py
electricitycostcalculator_gabetest/oadr_signal/__init__.py.bak
electricitycostcalculator_gabetest/oadr_signal/getDRSignal.py
electricitycostcalculator_gabetest/oadr_signal/getDRSignal.py.bak
electricitycostcalculator_gabetest/oadr_signal/getPelicanDREvents.py
electricitycostcalculator_gabetest/oadr_signal/getPelicanDREvents.py.bak
electricitycostcalculator_gabetest/oadr_signal/getSCEEvents.py
electricitycostcalculator_gabetest/oadr_signal/getSCEEvents.py.bak
electricitycostcalculator_gabetest/oadr_signal/settings_template.json
electricitycostcalculator_gabetest/oadr_signal/tariff_maps.py
electricitycostcalculator_gabetest/oadr_signal/tariff_maps.py.bak
electricitycostcalculator_gabetest/oadr_signal/utils.py
electricitycostcalculator_gabetest/oadr_signal/utils.py.bak
electricitycostcalculator_gabetest/openei_tariff/.gitignore
electricitycostcalculator_gabetest/openei_tariff/E-190-revised.json
electricitycostcalculator_gabetest/openei_tariff/PDP_events_ex.json
electricitycostcalculator_gabetest-0.1.2.dist-info/WHEEL
electricitycostcalculator_gabetest-0.1.2.dist-info/METADATA
electricitycostcalculator_gabetest-0.1.2.dist-info/RECORD
